anki_voiced/__init__.py
anki_voiced/__main__.py
anki_voiced/audio.py
anki_voiced/cli.py
anki_voiced/config.py
anki_voiced/csv_utils.py
anki_voiced/deck.py
anki_voiced/models.py
anki_voiced/preprocessing/__init__.py
anki_voiced/preprocessing/japanese.py
anki_voiced/templates/__init__.py
anki_voiced/templates/basic.py
anki_voiced/templates/cloze.py
anki_voiced/templates/double_card.py
anki_voiced-0.1.0.dist-info/METADATA
anki_voiced-0.1.0.dist-info/WHEEL
anki_voiced-0.1.0.dist-info/entry_points.txt
anki_voiced-0.1.0.dist-info/RECORD
