Metadata-Version: 2.4
Name: anki-voiced
Version: 0.1.0
Summary: Generate Anki flashcard decks with AI-voiced audio
Project-URL: Homepage, https://github.com/kakkoidev/anki-voiced
Project-URL: Repository, https://github.com/kakkoidev/anki-voiced
Project-URL: Issues, https://github.com/kakkoidev/anki-voiced/issues
License: MIT
Keywords: anki,audio,flashcards,language-learning,tts,vocabulary
Classifier: Development Status :: 4 - Beta
Classifier: Environment :: Console
Classifier: Intended Audience :: Education
Classifier: License :: OSI Approved :: MIT License
Classifier: Programming Language :: Python :: 3
Classifier: Programming Language :: Python :: 3.10
Classifier: Programming Language :: Python :: 3.11
Classifier: Programming Language :: Python :: 3.12
Classifier: Programming Language :: Python :: 3.13
Classifier: Topic :: Education
Classifier: Topic :: Multimedia :: Sound/Audio :: Speech
Requires-Python: >=3.10
Requires-Dist: fugashi>=1.5.2
Requires-Dist: genanki>=0.13.1
Requires-Dist: kokoro>=0.9.4
Requires-Dist: lameenc>=1.7.0
Requires-Dist: misaki[ja]>=0.9.4
Requires-Dist: numpy>=1.24.0
Requires-Dist: pydantic>=2.0.0
Requires-Dist: pyopenjtalk>=0.4.1
Requires-Dist: rich>=13.0.0
Requires-Dist: typer>=0.15.0
Requires-Dist: unidic>=1.1.0
Provides-Extra: dev
Requires-Dist: pytest-cov>=4.0.0; extra == 'dev'
Requires-Dist: pytest>=8.0.0; extra == 'dev'
Requires-Dist: ruff>=0.8.0; extra == 'dev'
Provides-Extra: py310
Requires-Dist: tomli>=2.0.0; extra == 'py310'
